dev_nectarpy-0.0.73.dist-info/licenses/LICENSE
dev_nectarpy-0.0.73.dist-info/licenses/NOTICE
nectarpy/__init__.py
nectarpy/lib.py
nectarpy/lib_v1.py
nectarpy/common/__init__.py
nectarpy/common/blockchain_init.py
nectarpy/common/encryption.py
nectarpy/config/EoaBond.json
nectarpy/config/QueryManager.json
nectarpy/config/USDC.json
nectarpy/config/UserRole.json
nectarpy/config/blockchain.json
nectarpy/config/starnode.json
dev_nectarpy-0.0.73.dist-info/METADATA
dev_nectarpy-0.0.73.dist-info/WHEEL
dev_nectarpy-0.0.73.dist-info/top_level.txt
dev_nectarpy-0.0.73.dist-info/RECORD
