Metadata-Version: 2.4
Name: dev-nectarpy
Version: 0.0.73
Summary: A Python API module designed to run queries on Nectar
Home-page: https://github.com/NectarProtocol/python-nectar-module
Author: Tamarin Health
Author-email: phil@tamarin.health
License: Apache License 2.0
Classifier: Programming Language :: Python :: 3
Classifier: License :: OSI Approved :: Apache Software License
Classifier: Operating System :: OS Independent
Requires-Python: >=3.11.6,<3.12
License-File: LICENSE
License-File: NOTICE
Requires-Dist: web3<7.0.0
Requires-Dist: python-dotenv==1.1.0
Requires-Dist: hpke==0.3.2
Requires-Dist: dill==0.3.9
Dynamic: author
Dynamic: author-email
Dynamic: classifier
Dynamic: description
Dynamic: description-content-type
Dynamic: home-page
Dynamic: license
Dynamic: license-file
Dynamic: requires-dist
Dynamic: requires-python
Dynamic: summary
